convertinhours/__init__.py
convertinhours/conversionhours.py
convertinhours/convertinhours.py
convertinhours/digitextractor.py
convertinhours/timetohours.py
convertinhours-1.0.dist-info/METADATA
convertinhours-1.0.dist-info/WHEEL
convertinhours-1.0.dist-info/top_level.txt
convertinhours-1.0.dist-info/RECORD
