Metadata-Version: 2.1
Name: convertinhours
Version: 1.0
Summary: UNKNOWN
Home-page: UNKNOWN
Author: Pratik Giri
Author-email: <mail@neuralnine.com>
License: UNKNOWN
Platform: UNKNOWN
Classifier: Development Status :: 1 - Planning
Classifier: Intended Audience :: Developers
Classifier: Programming Language :: Python :: 3
Classifier: Operating System :: Unix
Classifier: Operating System :: MacOS :: MacOS X
Classifier: Operating System :: Microsoft :: Windows
Requires-Dist: openpyxl
Requires-Dist: pandas
